aionasa/__init__.py
aionasa/asset.py
aionasa/client.py
aionasa/errors.py
aionasa/rate_limit.py
aionasa/utils.py
aionasa/apod/__init__.py
aionasa/apod/__main__.py
aionasa/apod/api.py
aionasa/apod/data.py
aionasa/epic/__init__.py
aionasa/epic/api.py
aionasa/epic/data.py
aionasa/exoplanet/__init__.py
aionasa/exoplanet/__main__.py
aionasa/exoplanet/_tests.py
aionasa/exoplanet/api.py
aionasa/exoplanet/query.py
aionasa/insight/__init__.py
aionasa/insight/__main__.py
aionasa/insight/api.py
aionasa/neows/__init__.py
aionasa/neows/api.py
aionasa/neows/data.py
aionasa/neows/paginators.py
aionasa-0.2.1.dist-info/LICENSE
aionasa-0.2.1.dist-info/METADATA
aionasa-0.2.1.dist-info/WHEEL
aionasa-0.2.1.dist-info/top_level.txt
aionasa-0.2.1.dist-info/RECORD
