Metadata-Version: 2.1
Name: aionasa
Version: 0.2.1
Summary: An async python wrapper for NASA open APIs.
Home-page: https://github.com/nwunderly/aionasa
Author: nwunderly
License: UNKNOWN
Project-URL: Documentation, https://aionasa.rtfd.org/
Platform: UNKNOWN
Classifier: Development Status :: 2 - Pre-Alpha
Classifier: License :: OSI Approved :: MIT License
Classifier: Intended Audience :: Developers
Classifier: Natural Language :: English
Classifier: Operating System :: OS Independent
Classifier: Programming Language :: Python :: 3.8
Classifier: Topic :: Internet
Classifier: Topic :: Software Development :: Libraries
Classifier: Topic :: Software Development :: Libraries :: Python Modules
Classifier: Topic :: Utilities
Requires-Python: >=3.8
Requires-Dist: aiohttp (~=3.6.2)
Requires-Dist: PyYAML (~=5.3.1)
Provides-Extra: docs
Requires-Dist: sphinx ; extra == 'docs'
Requires-Dist: sphinxcontrib-trio ; extra == 'docs'
